case_agent/__init__.py
case_agent/cli.py
case_agent/generator.py
case_agent-1.0.0.dist-info/licenses/LICENSE
case_agent-1.0.0.dist-info/METADATA
case_agent-1.0.0.dist-info/WHEEL
case_agent-1.0.0.dist-info/entry_points.txt
case_agent-1.0.0.dist-info/top_level.txt
case_agent-1.0.0.dist-info/RECORD
