Metadata-Version: 2.4
Name: case-agent
Version: 1.0.0
Summary: Contributor-safe agent framework for diagnostics and delivery
Author: QUEST
Author-email: QUEST <your-email@example.com>
Project-URL: Homepage, https://github.com/quest-dev/case-agent
Project-URL: Repository, https://github.com/quest-dev/case-agent
Requires-Python: >=3.7
License-File: LICENSE
Requires-Dist: PyYAML
Dynamic: author
Dynamic: license-file
Dynamic: requires-python
